{"id": "free_text_alert_20250403184103", "timestamp": "2025-04-03T18:41:03.345342", "type": "free_text_keystroke_anomaly", "confidence": 0.09295243681320582, "prediction_result": {"success": true, "predictions": [1, 0, 0, 0, 0, 0, 0, 0, 0, 0], "consecutive_zeros": 2, "is_anomaly": true, "confidence": 0.09295243681320582}, "keystroke_count": 49, "keystrokes": [{"Timestamp_Press": "2025-04-03T18:37:17.748259", "Timestamp_Release": "2025-04-03T18:37:18.002711", "Key Stroke": "Key.alt_l", "Application": "127.0.0.1:5000/api/keystroke/free-text/start/Fazil - My Workspace", "Hold Time": "0:00:00.254452", "Hold Time (seconds)": 0.254452}, {"Timestamp_Press": "2025-04-03T18:37:17.917993", "Timestamp_Release": "2025-04-03T18:37:18.057142", "Key Stroke": "Key.tab", "Application": "127.0.0.1:5000/api/keystroke/free-text/start/Fazil - My Workspace", "Hold Time": "0:00:00.139149", "Hold Time (seconds)": 0.139149}, {"Timestamp_Press": "2025-04-03T18:37:37.293858", "Timestamp_Release": "2025-04-03T18:37:37.413332", "Key Stroke": "'t'", "Application": "keystroke_processor.py - WebApp - Cursor [Administrator]", "Hold Time": "0:00:00.119474", "Hold Time (seconds)": 0.119474}, {"Timestamp_Press": "2025-04-03T18:37:37.443435", "Timestamp_Release": "2025-04-03T18:37:37.550210", "Key Stroke": "'h'", "Application": "keystroke_processor.py - WebApp - Cursor [Administrator]", "Hold Time": "0:00:00.106775", "Hold Time (seconds)": 0.106775}, {"Timestamp_Press": "2025-04-03T18:37:37.572494", "Timestamp_Release": "2025-04-03T18:37:37.683572", "Key Stroke": "'e'", "Application": "keystroke_processor.py - WebApp - Cursor [Administrator]", "Hold Time": "0:00:00.111078", "Hold Time (seconds)": 0.111078}, {"Timestamp_Press": "2025-04-03T18:37:37.780059", "Timestamp_Release": "2025-04-03T18:37:37.909376", "Key Stroke": "'q'", "Application": "keystroke_processor.py - WebApp - Cursor [Administrator]", "Hold Time": "0:00:00.129317", "Hold Time (seconds)": 0.129317}, {"Timestamp_Press": "2025-04-03T18:37:37.943351", "Timestamp_Release": "2025-04-03T18:37:38.019337", "Key Stroke": "'u'", "Application": "keystroke_processor.py - WebApp - Cursor [Administrator]", "Hold Time": "0:00:00.075986", "Hold Time (seconds)": 0.075986}, {"Timestamp_Press": "2025-04-03T18:37:38.114174", "Timestamp_Release": "2025-04-03T18:37:38.193800", "Key Stroke": "'i'", "Application": "keystroke_processor.py - WebApp - Cursor [Administrator]", "Hold Time": "0:00:00.079626", "Hold Time (seconds)": 0.079626}, {"Timestamp_Press": "2025-04-03T18:37:38.239659", "Timestamp_Release": "2025-04-03T18:37:38.354217", "Key Stroke": "'c'", "Application": "keystroke_processor.py - WebApp - Cursor [Administrator]", "Hold Time": "0:00:00.114558", "Hold Time (seconds)": 0.114558}, {"Timestamp_Press": "2025-04-03T18:37:38.423742", "Timestamp_Release": "2025-04-03T18:37:38.504162", "Key Stroke": "'k'", "Application": "keystroke_processor.py - WebApp - Cursor [Administrator]", "Hold Time": "0:00:00.080420", "Hold Time (seconds)": 0.08042}, {"Timestamp_Press": "2025-04-03T18:37:39.034632", "Timestamp_Release": "2025-04-03T18:37:39.149156", "Key Stroke": "'b'", "Application": "keystroke_processor.py - WebApp - Cursor [Administrator]", "Hold Time": "0:00:00.114524", "Hold Time (seconds)": 0.114524}, {"Timestamp_Press": "2025-04-03T18:37:39.184451", "Timestamp_Release": "2025-04-03T18:37:39.289843", "Key Stroke": "'r'", "Application": "keystroke_processor.py - WebApp - Cursor [Administrator]", "Hold Time": "0:00:00.105392", "Hold Time (seconds)": 0.105392}, {"Timestamp_Press": "2025-04-03T18:37:39.324390", "Timestamp_Release": "2025-04-03T18:37:39.435441", "Key Stroke": "'o'", "Application": "keystroke_processor.py - WebApp - Cursor [Administrator]", "Hold Time": "0:00:00.111051", "Hold Time (seconds)": 0.111051}, {"Timestamp_Press": "2025-04-03T18:37:39.485054", "Timestamp_Release": "2025-04-03T18:37:39.585569", "Key Stroke": "'w'", "Application": "keystroke_processor.py - WebApp - Cursor [Administrator]", "Hold Time": "0:00:00.100515", "Hold Time (seconds)": 0.100515}, {"Timestamp_Press": "2025-04-03T18:37:39.605285", "Timestamp_Release": "2025-04-03T18:37:39.719576", "Key Stroke": "'n'", "Application": "keystroke_processor.py - WebApp - Cursor [Administrator]", "Hold Time": "0:00:00.114291", "Hold Time (seconds)": 0.114291}, {"Timestamp_Press": "2025-04-03T18:37:39.855120", "Timestamp_Release": "2025-04-03T18:37:39.964943", "Key Stroke": "Key.space", "Application": "keystroke_processor.py - WebApp - Cursor [Administrator]", "Hold Time": "0:00:00.109823", "Hold Time (seconds)": 0.109823}, {"Timestamp_Press": "2025-04-03T18:37:40.001209", "Timestamp_Release": "2025-04-03T18:37:40.110531", "Key Stroke": "'f'", "Application": "keystroke_processor.py - WebApp - Cursor [Administrator]", "Hold Time": "0:00:00.109322", "Hold Time (seconds)": 0.109322}, {"Timestamp_Press": "2025-04-03T18:37:40.535834", "Timestamp_Release": "2025-04-03T18:37:40.641006", "Key Stroke": "'o'", "Application": "keystroke_processor.py - WebApp - Cursor [Administrator]", "Hold Time": "0:00:00.105172", "Hold Time (seconds)": 0.105172}, {"Timestamp_Press": "2025-04-03T18:37:40.696090", "Timestamp_Release": "2025-04-03T18:37:40.806695", "Key Stroke": "'x'", "Application": "keystroke_processor.py - WebApp - Cursor [Administrator]", "Hold Time": "0:00:00.110605", "Hold Time (seconds)": 0.110605}, {"Timestamp_Press": "2025-04-03T18:37:40.841773", "Timestamp_Release": "2025-04-03T18:37:40.951306", "Key Stroke": "Key.space", "Application": "keystroke_processor.py - WebApp - Cursor [Administrator]", "Hold Time": "0:00:00.109533", "Hold Time (seconds)": 0.109533}, {"Timestamp_Press": "2025-04-03T18:37:41.906968", "Timestamp_Release": "2025-04-03T18:37:42.022106", "Key Stroke": "'a'", "Application": "keystroke_processor.py - WebApp - Cursor [Administrator]", "Hold Time": "0:00:00.115138", "Hold Time (seconds)": 0.115138}, {"Timestamp_Press": "2025-04-03T18:37:42.116907", "Timestamp_Release": "2025-04-03T18:37:42.232256", "Key Stroke": "'b'", "Application": "keystroke_processor.py - WebApp - Cursor [Administrator]", "Hold Time": "0:00:00.115349", "Hold Time (seconds)": 0.115349}, {"Timestamp_Press": "2025-04-03T18:37:42.273125", "Timestamp_Release": "2025-04-03T18:37:42.357235", "Key Stroke": "'c'", "Application": "keystroke_processor.py - WebApp - Cursor [Administrator]", "Hold Time": "0:00:00.084110", "Hold Time (seconds)": 0.08411}, {"Timestamp_Press": "2025-04-03T18:37:42.517162", "Timestamp_Release": "2025-04-03T18:37:42.632303", "Key Stroke": "'d'", "Application": "keystroke_processor.py - WebApp - Cursor [Administrator]", "Hold Time": "0:00:00.115141", "Hold Time (seconds)": 0.115141}, {"Timestamp_Press": "2025-04-03T18:37:42.732416", "Timestamp_Release": "2025-04-03T18:37:42.823552", "Key Stroke": "'e'", "Application": "keystroke_processor.py - WebApp - Cursor [Administrator]", "Hold Time": "0:00:00.091136", "Hold Time (seconds)": 0.091136}, {"Timestamp_Press": "2025-04-03T18:37:42.962785", "Timestamp_Release": "2025-04-03T18:37:43.057976", "Key Stroke": "'f'", "Application": "keystroke_processor.py - WebApp - Cursor [Administrator]", "Hold Time": "0:00:00.095191", "Hold Time (seconds)": 0.095191}, {"Timestamp_Press": "2025-04-03T18:37:43.173058", "Timestamp_Release": "2025-04-03T18:37:43.262232", "Key Stroke": "'g'", "Application": "keystroke_processor.py - WebApp - Cursor [Administrator]", "Hold Time": "0:00:00.089174", "Hold Time (seconds)": 0.089174}, {"Timestamp_Press": "2025-04-03T18:37:43.363232", "Timestamp_Release": "2025-04-03T18:37:43.443169", "Key Stroke": "'h'", "Application": "keystroke_processor.py - WebApp - Cursor [Administrator]", "Hold Time": "0:00:00.079937", "Hold Time (seconds)": 0.079937}, {"Timestamp_Press": "2025-04-03T18:37:43.584006", "Timestamp_Release": "2025-04-03T18:37:43.673549", "Key Stroke": "'i'", "Application": "keystroke_processor.py - WebApp - Cursor [Administrator]", "Hold Time": "0:00:00.089543", "Hold Time (seconds)": 0.089543}, {"Timestamp_Press": "2025-04-03T18:37:43.738756", "Timestamp_Release": "2025-04-03T18:37:43.858529", "Key Stroke": "'j'", "Application": "keystroke_processor.py - WebApp - Cursor [Administrator]", "Hold Time": "0:00:00.119773", "Hold Time (seconds)": 0.119773}, {"Timestamp_Press": "2025-04-03T18:37:43.973562", "Timestamp_Release": "2025-04-03T18:37:44.073836", "Key Stroke": "'k'", "Application": "keystroke_processor.py - WebApp - Cursor [Administrator]", "Hold Time": "0:00:00.100274", "Hold Time (seconds)": 0.100274}, {"Timestamp_Press": "2025-04-03T18:37:44.183779", "Timestamp_Release": "2025-04-03T18:37:44.268594", "Key Stroke": "'l'", "Application": "keystroke_processor.py - WebApp - Cursor [Administrator]", "Hold Time": "0:00:00.084815", "Hold Time (seconds)": 0.084815}, {"Timestamp_Press": "2025-04-03T18:37:44.374874", "Timestamp_Release": "2025-04-03T18:37:44.454493", "Key Stroke": "'m'", "Application": "keystroke_processor.py - WebApp - Cursor [Administrator]", "Hold Time": "0:00:00.079619", "Hold Time (seconds)": 0.079619}, {"Timestamp_Press": "2025-04-03T18:38:39.742089", "Timestamp_Release": "2025-04-03T18:38:39.847877", "Key Stroke": "Key.enter", "Application": "keystroke_processor.py - WebApp - Cursor [Administrator]", "Hold Time": "0:00:00.105788", "Hold Time (seconds)": 0.105788}, {"Timestamp_Press": "2025-04-03T18:38:45.547605", "Timestamp_Release": "2025-04-03T18:38:45.722184", "Key Stroke": "'h'", "Application": "keystroke_processor.py - WebApp - Cursor [Administrator]", "Hold Time": "0:00:00.174579", "Hold Time (seconds)": 0.174579}, {"Timestamp_Press": "2025-04-03T18:38:45.916695", "Timestamp_Release": "2025-04-03T18:38:46.027205", "Key Stroke": "'o'", "Application": "keystroke_processor.py - WebApp - Cursor [Administrator]", "Hold Time": "0:00:00.110510", "Hold Time (seconds)": 0.11051}, {"Timestamp_Press": "2025-04-03T18:38:46.643426", "Timestamp_Release": "2025-04-03T18:38:46.703195", "Key Stroke": "'w'", "Application": "keystroke_processor.py - WebApp - Cursor [Administrator]", "Hold Time": "0:00:00.059769", "Hold Time (seconds)": 0.059769}, {"Timestamp_Press": "2025-04-03T18:38:46.824085", "Timestamp_Release": "2025-04-03T18:38:46.918037", "Key Stroke": "Key.space", "Application": "keystroke_processor.py - WebApp - Cursor [Administrator]", "Hold Time": "0:00:00.093952", "Hold Time (seconds)": 0.093952}, {"Timestamp_Press": "2025-04-03T18:38:46.978013", "Timestamp_Release": "2025-04-03T18:38:47.083221", "Key Stroke": "'t'", "Application": "keystroke_processor.py - WebApp - Cursor [Administrator]", "Hold Time": "0:00:00.105208", "Hold Time (seconds)": 0.105208}, {"Timestamp_Press": "2025-04-03T18:38:47.253196", "Timestamp_Release": "2025-04-03T18:38:47.373595", "Key Stroke": "'o'", "Application": "keystroke_processor.py - WebApp - Cursor [Administrator]", "Hold Time": "0:00:00.120399", "Hold Time (seconds)": 0.120399}, {"Timestamp_Press": "2025-04-03T18:38:47.398093", "Timestamp_Release": "2025-04-03T18:38:47.518360", "Key Stroke": "Key.space", "Application": "keystroke_processor.py - WebApp - Cursor [Administrator]", "Hold Time": "0:00:00.120267", "Hold Time (seconds)": 0.120267}, {"Timestamp_Press": "2025-04-03T18:38:47.603582", "Timestamp_Release": "2025-04-03T18:38:47.713798", "Key Stroke": "'f'", "Application": "keystroke_processor.py - WebApp - Cursor [Administrator]", "Hold Time": "0:00:00.110216", "Hold Time (seconds)": 0.110216}, {"Timestamp_Press": "2025-04-03T18:38:47.798807", "Timestamp_Release": "2025-04-03T18:38:47.828944", "Key Stroke": "'i'", "Application": "keystroke_processor.py - WebApp - Cursor [Administrator]", "Hold Time": "0:00:00.030137", "Hold Time (seconds)": 0.030137}, {"Timestamp_Press": "2025-04-03T18:38:49.115006", "Timestamp_Release": "2025-04-03T18:38:49.244702", "Key Stroke": "'x'", "Application": "keystroke_processor.py - WebApp - Cursor [Administrator]", "Hold Time": "0:00:00.129696", "Hold Time (seconds)": 0.129696}, {"Timestamp_Press": "2025-04-03T18:38:49.339549", "Timestamp_Release": "2025-04-03T18:38:49.469965", "Key Stroke": "Key.space", "Application": "keystroke_processor.py - WebApp - Cursor [Administrator]", "Hold Time": "0:00:00.130416", "Hold Time (seconds)": 0.130416}, {"Timestamp_Press": "2025-04-03T18:38:49.500295", "Timestamp_Release": "2025-04-03T18:38:49.595323", "Key Stroke": "'t'", "Application": "keystroke_processor.py - WebApp - Cursor [Administrator]", "Hold Time": "0:00:00.095028", "Hold Time (seconds)": 0.095028}, {"Timestamp_Press": "2025-04-03T18:38:49.685521", "Timestamp_Release": "2025-04-03T18:38:49.775661", "Key Stroke": "'h'", "Application": "keystroke_processor.py - WebApp - Cursor [Administrator]", "Hold Time": "0:00:00.090140", "Hold Time (seconds)": 0.09014}, {"Timestamp_Press": "2025-04-03T18:38:49.846579", "Timestamp_Release": "2025-04-03T18:38:49.940680", "Key Stroke": "'u'", "Application": "keystroke_processor.py - WebApp - Cursor [Administrator]", "Hold Time": "0:00:00.094101", "Hold Time (seconds)": 0.094101}, {"Timestamp_Press": "2025-04-03T18:38:50.104895", "Timestamp_Release": "2025-04-03T18:38:50.175297", "Key Stroke": "'s'", "Application": "keystroke_processor.py - WebApp - Cursor [Administrator]", "Hold Time": "0:00:00.070402", "Hold Time (seconds)": 0.070402}], "free_text_collection_progress": {"collected": 49, "target": 10000, "percentage": 0.5}}